{
  "tool" : "jekyll",
  "paths": {
    "resources": ["resources", "examples"],
    "pages": "pages",
    "temp": "temp",
    "output": "output",
    "qa": "qa",
    "specification": "http://hl7.org/fhir/STU3/"
  },
  "defaults": {
    "Any": {
      "template-format": "instance-template-format.html",
      "template-base": "instance-template-base.html"
    },
    "StructureDefinition" : {
      "template-base": "instance-template-sd.html",
      "template-mappings": "instance-template-mappings.html",
      "template-defns": "instance-template-definitions.html"
    }
  },
  "version" : "3.0.1",
  "logging": ["init", "progress", "context", "html", "tx"],
  "sct-edition" : "http://snomed.info/sct/731000124108",
  "extraTemplates": [
    "mappings"
  ],
  "canonicalBase": "http://hl7.org/fhir/ig/PDDI-CDS",
  "source": "",
  "spreadsheets": [
  ],
  "resources": {
   "ValueSet/aldosterone-antagonists": {
      "source": "valueset-aldosterone-antagonists.xml",
      "base": "Valueset-aldosterone-antagonists.html"
    },
    "ValueSet/misoprostol": {
      "source": "valueset-misoprostol.xml",
      "base": "Valueset-misoprostol.html"
    },
    "ValueSet/NSAID": {
      "source": "valueset-NSAID.json",
      "base": "Valueset-NSAID.html"
    },
    "ValueSet/warfarin": {
      "source": "valueset-warfarin.xml",
      "base": "valueset-warfarin.html"
    },
    "ValueSet/Hx-UGIB-snomed": {
      "source": "valueset-Hx-UGIB-snomed.xml",
      "base": "Valueset-Hx-UGIB-snomed.html"
    },
    "ValueSet/NSAID-exclude": {
      "source": "valueset-NSAID-exclude.json",
      "base": "Valueset-NSAID-exclude.html"
    },
    "ValueSet/proton-pump-inhibitors": {
      "source": "valueset-proton-pump-inhibitors.xml",
      "base": "Valueset-proton-pump-inhibitors.html"
    }
  }
}
