<?xml version="1.0" encoding="utf-8"?>
<ValueSet xmlns="http://hl7.org/fhir">
    <url value="http://hl7.org/fhir/ig/PDDI-CDS/ValueSet/valueset-NSAIDS"/>
    <id value="valueset-NSAIDS"/>
    <version value="US 1.0"/>
    <name value="valueset-NSAIDS"/>
    <title value="Nonsteroidal Anti-inflammatory Drugs Value Set"/>
    <status value="draft"/>
    <date value="2018-07-02"/>
    <publisher value="PDDI CDS"/>
    <contact>
        <name value="Richard Boyce boycerd@upmc.edu"/>
    </contact>
    <description value="ValueSet of ValueSets containing drug identifiers for each member in the
    Established Pharmacologic Class (EPC) Nonsteroidal Anti-inflammatory Drug class (id: N0000175722).
    Member by RxNorm: getRelatedByType (BN,BPCK,GPCK,IN,MIN,PIN,SBD,SBDC,SBDF,SBDG,SCD,SCDC,SCDF,SCDG)"/>
    <jurisdiction>
        <coding>
            <system value="urn:iso:std:iso:3166"/>
            <code value="US"/>
            <display value="United States of America"/>
        </coding>
    </jurisdiction>
    <purpose value="Provide NSAID class terminology for PDDI CDS FHIR resources"/>
    <copyright value="Attribution CC BY"/>
    <compose>
        <include>
            <valueSet value="http://hl7.org/fhir/ig/PDDI-CDS/ValueSet/valueset-aspirin.xml"/>
        </include>
        <include>
            <valueSet value="http://hl7.org/fhir/ig/PDDI-CDS/ValueSet/valueset-bromfenac.xml"/>
        </include>
        <include>
            <valueSet value="http://hl7.org/fhir/ig/PDDI-CDS/ValueSet/valueset-celecoxib.xml"/>
        </include>
        <include>
            <valueSet value="http://hl7.org/fhir/ig/PDDI-CDS/ValueSet/valueset-diclofenac.xml"/>
        </include>
        <include>
            <valueSet value="http://hl7.org/fhir/ig/PDDI-CDS/ValueSet/valueset-diflunisal.xml"/>
        </include>
        <include>
            <valueSet value="http://hl7.org/fhir/ig/PDDI-CDS/ValueSet/valueset-etodolac.xml"/>
        </include>
        <include>
            <valueSet value="http://hl7.org/fhir/ig/PDDI-CDS/ValueSet/valueset-fenoprofen.xml"/>
        </include>
        <include>
            <valueSet value="http://hl7.org/fhir/ig/PDDI-CDS/ValueSet/valueset-flurbiprofen.xml"/>
        </include>
        <include>
            <valueSet value="http://hl7.org/fhir/ig/PDDI-CDS/ValueSet/valueset-ibuprofen.xml"/>
        </include>
        <include>
            <valueSet value="http://hl7.org/fhir/ig/PDDI-CDS/ValueSet/valueset-indomethacin.xml"/>
        </include>
        <include>
            <valueSet value="http://hl7.org/fhir/ig/PDDI-CDS/ValueSet/valueset-ketoprofen.xml"/>
        </include>
        <include>
            <valueSet value="http://hl7.org/fhir/ig/PDDI-CDS/ValueSet/valueset-ketorolac.xml"/>
        </include>
        <include>
            <valueSet value="http://hl7.org/fhir/ig/PDDI-CDS/ValueSet/valueset-mefenamate.xml"/>
        </include>
        <include>
            <valueSet value="http://hl7.org/fhir/ig/PDDI-CDS/ValueSet/valueset-meloxicam.xml"/>
        </include>
        <include>
            <valueSet value="http://hl7.org/fhir/ig/PDDI-CDS/ValueSet/valueset-nabumetone.xml"/>
        </include>
        <include>
            <valueSet value="http://hl7.org/fhir/ig/PDDI-CDS/ValueSet/valueset-naproxen.xml"/>
        </include>
        <include>
            <valueSet value="http://hl7.org/fhir/ig/PDDI-CDS/ValueSet/valueset-nepafenac.xml"/>
        </include>
        <include>
            <valueSet value="http://hl7.org/fhir/ig/PDDI-CDS/ValueSet/valueset-oxaprozin.xml"/>
        </include>
        <include>
            <valueSet value="http://hl7.org/fhir/ig/PDDI-CDS/ValueSet/valueset-piroxicam.xml"/>
        </include>
        <include>
            <valueSet value="http://hl7.org/fhir/ig/PDDI-CDS/ValueSet/valueset-sulindac.xml"/>
        </include>
        <include>
            <valueSet value="http://hl7.org/fhir/ig/PDDI-CDS/ValueSet/valueset-tolmetin.xml"/>
        </include>
    </compose>
</ValueSet>
