{"resourceType":"ValueSet","expansion":{"identifier":"urn:uuid:b2c44fcc-dae8-4826-807e-4c6efa459bda","timestamp":"2018-07-15T21:10:47.211Z","parameter":[{"name":"limitedExpansion","valueString":"-1"},{"name":"version","valueString":"http://www.nlm.nih.gov/research/umls/rxnorm?version=??"}],"contains":[{"system":"http://www.nlm.nih.gov/research/umls/rxnorm","code":"31448","display":"nabumetone"},{"system":"http://www.nlm.nih.gov/research/umls/rxnorm","code":"105953","display":"nabumetone 100 MG/ML Oral Suspension"},{"system":"http://www.nlm.nih.gov/research/umls/rxnorm","code":"311892","display":"nabumetone 500 MG Oral Tablet"},{"system":"http://www.nlm.nih.gov/research/umls/rxnorm","code":"311893","display":"nabumetone 750 MG Oral Tablet"},{"system":"http://www.nlm.nih.gov/research/umls/rxnorm","code":"392641","display":"nabumetone 2.5 MG/ML Oral Solution"},{"system":"http://www.nlm.nih.gov/research/umls/rxnorm","code":"335255","display":"nabumetone 100 MG/ML"},{"system":"http://www.nlm.nih.gov/research/umls/rxnorm","code":"343093","display":"nabumetone 750 MG"},{"system":"http://www.nlm.nih.gov/research/umls/rxnorm","code":"343109","display":"nabumetone 500 MG"},{"system":"http://www.nlm.nih.gov/research/umls/rxnorm","code":"393527","display":"nabumetone 2.5 MG/ML"},{"system":"http://www.nlm.nih.gov/research/umls/rxnorm","code":"372976","display":"nabumetone Oral Suspension"},{"system":"http://www.nlm.nih.gov/research/umls/rxnorm","code":"378684","display":"nabumetone Oral Tablet"},{"system":"http://www.nlm.nih.gov/research/umls/rxnorm","code":"393528","display":"nabumetone Oral Solution"},{"system":"http://www.nlm.nih.gov/research/umls/rxnorm","code":"1158378","display":"nabumetone Oral Liquid Product"},{"system":"http://www.nlm.nih.gov/research/umls/rxnorm","code":"1158379","display":"nabumetone Oral Product"},{"system":"http://www.nlm.nih.gov/research/umls/rxnorm","code":"1158380","display":"nabumetone Pill"},{"system":"http://www.nlm.nih.gov/research/umls/rxnorm","code":"31448","display":"nabumetone"},{"system":"http://www.nlm.nih.gov/research/umls/rxnorm","code":"105953","display":"nabumetone 100 MG/ML Oral Suspension"},{"system":"http://www.nlm.nih.gov/research/umls/rxnorm","code":"311892","display":"nabumetone 500 MG Oral Tablet"},{"system":"http://www.nlm.nih.gov/research/umls/rxnorm","code":"311893","display":"nabumetone 750 MG Oral Tablet"},{"system":"http://www.nlm.nih.gov/research/umls/rxnorm","code":"392641","display":"nabumetone 2.5 MG/ML Oral Solution"},{"system":"http://www.nlm.nih.gov/research/umls/rxnorm","code":"335255","display":"nabumetone 100 MG/ML"},{"system":"http://www.nlm.nih.gov/research/umls/rxnorm","code":"343093","display":"nabumetone 750 MG"},{"system":"http://www.nlm.nih.gov/research/umls/rxnorm","code":"343109","display":"nabumetone 500 MG"},{"system":"http://www.nlm.nih.gov/research/umls/rxnorm","code":"393527","display":"nabumetone 2.5 MG/ML"},{"system":"http://www.nlm.nih.gov/research/umls/rxnorm","code":"372976","display":"nabumetone Oral Suspension"},{"system":"http://www.nlm.nih.gov/research/umls/rxnorm","code":"378684","display":"nabumetone Oral Tablet"},{"system":"http://www.nlm.nih.gov/research/umls/rxnorm","code":"393528","display":"nabumetone Oral Solution"},{"system":"http://www.nlm.nih.gov/research/umls/rxnorm","code":"1158378","display":"nabumetone Oral Liquid Product"},{"system":"http://www.nlm.nih.gov/research/umls/rxnorm","code":"1158379","display":"nabumetone Oral Product"},{"system":"http://www.nlm.nih.gov/research/umls/rxnorm","code":"1158380","display":"nabumetone Pill"}]}}